LICENSE
MANIFEST.in
README.md
setup.cfg
setup.py
EVELink.egg-info/PKG-INFO
EVELink.egg-info/SOURCES.txt
EVELink.egg-info/dependency_links.txt
EVELink.egg-info/top_level.txt
bin/evelink
evelink/__init__.py
evelink/account.py
evelink/api.py
evelink/char.py
evelink/constants.py
evelink/corp.py
evelink/eve.py
evelink/map.py
evelink/server.py
evelink/appengine/__init__.py
evelink/appengine/account.py
evelink/appengine/api.py
evelink/appengine/char.py
evelink/appengine/corp.py
evelink/appengine/eve.py
evelink/appengine/map.py
evelink/appengine/server.py
evelink/cache/__init__.py
evelink/cache/shelf.py
evelink/cache/sqlite.py
evelink/parsing/__init__.py
evelink/parsing/assets.py
evelink/parsing/bookmarks.py
evelink/parsing/contact_list.py
evelink/parsing/contract_bids.py
evelink/parsing/contract_items.py
evelink/parsing/contracts.py
evelink/parsing/industry_jobs.py
evelink/parsing/kills.py
evelink/parsing/orders.py
evelink/parsing/planetary_interactions.py
evelink/parsing/wallet_journal.py
evelink/parsing/wallet_transactions.py
evelink/thirdparty/__init__.py
evelink/thirdparty/eve_central.py
evelink/thirdparty/eve_who.py
evelink/thirdparty/six.py