Metadata-Version: 1.1
Name: EVELink
Version: 0.7.1
Summary: Python Bindings for the EVE Online API
Home-page: https://github.com/eve-val/evelink
Author: Amber Yust
Author-email: amber.yust@gmail.com
License: MIT License
Download-URL: https://github.com/eve-val/evelink/downloads
Platform: UNKNOWN
Classifier: Development Status :: 4 - Beta
Classifier: License :: OSI Approved :: MIT License
Classifier: Intended Audience :: Developers
Classifier: Operating System :: OS Independent
Classifier: Programming Language :: Python :: 2.6
Classifier: Programming Language :: Python :: 2.7
Classifier: Programming Language :: Python :: 3
Classifier: Topic :: Games/Entertainment
Classifier: Topic :: Software Development :: Libraries :: Python Modules
Requires: six
Provides: evelink
